openfisca_survey_manager/__init__.py
openfisca_survey_manager/aggregates.py
openfisca_survey_manager/calibration.py
openfisca_survey_manager/calmar.py
openfisca_survey_manager/coicop.py
openfisca_survey_manager/config.py
openfisca_survey_manager/google_colab.py
openfisca_survey_manager/input_dataframe_generator.py
openfisca_survey_manager/matching.py
openfisca_survey_manager/paths.py
openfisca_survey_manager/read_dbf.py
openfisca_survey_manager/read_sas.py
openfisca_survey_manager/read_spss.py
openfisca_survey_manager/simulation_builder.py
openfisca_survey_manager/simulations.py
openfisca_survey_manager/statshelpers.py
openfisca_survey_manager/survey_collections.py
openfisca_survey_manager/surveys.py
openfisca_survey_manager/tables.py
openfisca_survey_manager/temporary.py
openfisca_survey_manager/utils.py
openfisca_survey_manager/variables.py
openfisca_survey_manager/assets/COICOP/1998/nomenclature_coicop1998_source_by_classes.csv
openfisca_survey_manager/assets/COICOP/1998/nomenclature_coicop1998_source_by_divisions.csv
openfisca_survey_manager/assets/COICOP/1998/nomenclature_coicop1998_source_by_groupes.csv
openfisca_survey_manager/assets/COICOP/1998/nomenclature_coicop1998_source_by_postes.csv
openfisca_survey_manager/assets/COICOP/1998/nomenclature_coicop1998_source_by_sous_classes.csv
openfisca_survey_manager/assets/COICOP/2016/nomenclature_coicop2016_source_by_classes.xls
openfisca_survey_manager/assets/COICOP/2016/nomenclature_coicop2016_source_by_divisions.xls
openfisca_survey_manager/assets/COICOP/2016/nomenclature_coicop2016_source_by_groupes.xls
openfisca_survey_manager/assets/COICOP/2016/nomenclature_coicop2016_source_by_postes.xls
openfisca_survey_manager/assets/COICOP/2016/nomenclature_coicop2016_source_by_sous_classes.xls
openfisca_survey_manager/config_files_templates/__init__.py
openfisca_survey_manager/config_files_templates/config_template.ini
openfisca_survey_manager/config_files_templates/raw_data_template.ini
openfisca_survey_manager-4.0.1.dist-info/licenses/LICENSE.AGPL.txt
openfisca_survey_manager-4.0.1.dist-info/METADATA
openfisca_survey_manager-4.0.1.dist-info/WHEEL
openfisca_survey_manager-4.0.1.dist-info/entry_points.txt
openfisca_survey_manager-4.0.1.dist-info/top_level.txt
openfisca_survey_manager-4.0.1.dist-info/RECORD
