Metadata-Version: 2.4
Name: OpenFisca-Survey-Manager
Version: 4.0.1
Summary: A tool for managing survey/administrative data and import them in OpenFisca
Author-email: OpenFisca Team <contact@openfisca.fr>
License-Expression: AGPL-3.0-or-later
Project-URL: Homepage, https://github.com/openfisca/openfisca-survey-manager
Project-URL: Repository, https://github.com/openfisca/openfisca-survey-manager
Project-URL: Issues, https://github.com/openfisca/openfisca-survey-manager/issues
Project-URL: Changelog, https://github.com/openfisca/openfisca-survey-manager/blob/main/CHANGELOG.md
Keywords: microsimulation,tax,benefit,rac,rules-as-code,survey,data
Classifier: Development Status :: 5 - Production/Stable
Classifier: Operating System :: POSIX
Classifier: Programming Language :: Python
Classifier: Programming Language :: Python :: 3.9
Classifier: Programming Language :: Python :: 3.10
Classifier: Programming Language :: Python :: 3.11
Classifier: Topic :: Scientific/Engineering :: Information Analysis
Requires-Python: >=3.9
License-File: LICENSE.AGPL.txt
Requires-Dist: chardet<6.0,>=5.1.0
Requires-Dist: configparser<8.0,>=5.3.0
Requires-Dist: humanize<5.0,>=4.6.0
Requires-Dist: numpy<2.0,>=1.24.2
Requires-Dist: openfisca-core<45.0.0,>=43.0.0
Requires-Dist: pandas<3.0,>=2.0.3
Requires-Dist: pyarrow<19.0.0,>=13.0.0
Requires-Dist: pyxdg<0.29,>=0.28
Requires-Dist: PyYAML<7.0,>=6.0
Requires-Dist: tables<4.0,>=3.8.0
Requires-Dist: tabulate<0.10.0,>=0.9.0
Requires-Dist: weightedcalcs<0.2.0,>=0.1.2
Requires-Dist: wquantiles<0.7,>=0.6
Provides-Extra: matching
Requires-Dist: rpy2<4.0,>=3.5.10; extra == "matching"
Provides-Extra: dev
Requires-Dist: coveralls<5.0,>=3.3.1; extra == "dev"
Requires-Dist: openfisca-country-template<8.0.0,>=7.1.5; extra == "dev"
Requires-Dist: pyreadstat<1.3,>=1.2.1; extra == "dev"
Requires-Dist: pytest; extra == "dev"
Requires-Dist: pytest-cov; extra == "dev"
Requires-Dist: scipy<2.0,>=1.10.1; extra == "dev"
Requires-Dist: pytest-order; extra == "dev"
Requires-Dist: ruff; extra == "dev"
Requires-Dist: isort; extra == "dev"
Requires-Dist: pre-commit; extra == "dev"
Requires-Dist: ipdb; extra == "dev"
Requires-Dist: pdbpp; extra == "dev"
Provides-Extra: casd
Requires-Dist: pytest; extra == "casd"
Requires-Dist: scipy<2.0,>=1.10.1; extra == "casd"
Requires-Dist: ruff; extra == "casd"
Requires-Dist: isort; extra == "casd"
Provides-Extra: sas
Requires-Dist: pyreadstat<1.3,>=1.2.1; extra == "sas"
Requires-Dist: sas7bdat<3.0,>=2.2.3; extra == "sas"
Dynamic: license-file
